mailer/__init__.py
mailer/admin.py
mailer/apps.py
mailer/backend.py
mailer/engine.py
mailer/models.py
mailer/postgres.py
mailer/locale/ja/LC_MESSAGES/django.po
mailer/locale/ru/LC_MESSAGES/django.po
mailer/management/__init__.py
mailer/management/helpers.py
mailer/management/commands/__init__.py
mailer/management/commands/purge_mail_log.py
mailer/management/commands/retry_deferred.py
mailer/management/commands/runmailer.py
mailer/management/commands/runmailer_pg.py
mailer/management/commands/send_mail.py
mailer/migrations/0001_initial.py
mailer/migrations/0002_auto_20150720_1433.py
mailer/migrations/0003_messagelog_message_id.py
mailer/migrations/0004_auto_20190920_1512.py
mailer/migrations/0005_id_bigautofield.py
mailer/migrations/0006_message_retry_count.py
mailer/migrations/0007_alter_messagelog_message_data.py
mailer/migrations/__init__.py
django_mailer-2.3.2.dist-info/AUTHORS
django_mailer-2.3.2.dist-info/LICENSE
django_mailer-2.3.2.dist-info/METADATA
django_mailer-2.3.2.dist-info/WHEEL
django_mailer-2.3.2.dist-info/top_level.txt
django_mailer-2.3.2.dist-info/RECORD
