Metadata-Version: 2.1
Name: django-mailer
Version: 2.3.2
Summary: A reusable Django app for queuing the sending of email
Home-page: http://github.com/pinax/django-mailer/
Author: Pinax Team
Author-email: developers@pinaxproject.com
License: UNKNOWN
Platform: UNKNOWN
Classifier: Development Status :: 5 - Production/Stable
Classifier: Environment :: Web Environment
Classifier: Intended Audience :: Developers
Classifier: License :: OSI Approved :: MIT License
Classifier: Operating System :: OS Independent
Classifier: Programming Language :: Python
Classifier: Programming Language :: Python :: 3.8
Classifier: Programming Language :: Python :: 3.9
Classifier: Programming Language :: Python :: 3.10
Classifier: Programming Language :: Python :: 3.11
Classifier: Framework :: Django
Requires-Python: >=3.8
License-File: LICENSE
License-File: AUTHORS
